<?xml version="1.0" encoding="UTF-8" standalone="no"?>
<xml>
    <Tenistas>
        <Tenista>
            <Ranking>1</Ranking>
            <Nombre>Rafa</Nombre>
            <Apellido>Nadal</Apellido>
            <Grand-Slams>22</Grand-Slams>
        </Tenista>
        <Tenista>
            <Ranking>2</Ranking>
            <Nombre>Novak</Nombre>
            <Apellido>Djokovic</Apellido>
            <Grand-Slams>21</Grand-Slams>
        </Tenista>
        <Tenista>
            <Ranking>3</Ranking>
            <Nombre>Roger</Nombre>
            <Apellido>Federer</Apellido>
            <Grand-Slams>20</Grand-Slams>
        </Tenista>
        <Tenista>
            <Ranking>4</Ranking>
            <Nombre>Pete</Nombre>
            <Apellido>Sampras</Apellido>
            <Grand-Slams>14</Grand-Slams>
        </Tenista>
        <Tenista>
            <Ranking>5</Ranking>
            <Nombre>Bjorn</Nombre>
            <Apellido>Borg</Apellido>
            <Grand-Slams>11</Grand-Slams>
        </Tenista>
        <Tenista>
            <Ranking>6</Ranking>
            <Nombre>Ivan</Nombre>
            <Apellido>Lendl</Apellido>
            <Grand-Slams>8</Grand-Slams>
        </Tenista>
        <Tenista>
            <Ranking>7</Ranking>
            <Nombre>Jimmy</Nombre>
            <Apellido>Connors</Apellido>
            <Grand-Slams>8</Grand-Slams>
        </Tenista>
        <Tenista>
            <Ranking>8</Ranking>
            <Nombre>Andre</Nombre>
            <Apellido>Agassi</Apellido>
            <Grand-Slams>8</Grand-Slams>
        </Tenista>
        <Tenista>
            <Ranking>9</Ranking>
            <Nombre>John</Nombre>
            <Apellido>McKenroe</Apellido>
            <Grand-Slams>7</Grand-Slams>
        </Tenista>
        <Tenista>
            <Ranking>10</Ranking>
            <Nombre>Mats</Nombre>
            <Apellido>Wilander</Apellido>
            <Grand-Slams>7</Grand-Slams>
        </Tenista>
    </Tenistas>
</xml>
